edgedetect/edgedetect.v
`timescale 1ns / 1ps
module edgedetect
			(
				input	clk,rst,
				input	data_in,
				output	reg fle
			);

	reg [2:0] pipe;
	wire fallingedge = (pipe[2:1] == 2'b10);

	always@ (posedge clk) begin pipe <= {pipe[1:0],data_in}; end

	always@ (posedge clk) begin
		if (rst) begin
			fle <= 0;
		end else if (fallingedge) begin
			fle <= 1;
		end
	end

	
endmodule

edgedetect/tb_edgedetect.v
`timescale 1ns / 1ps

module tb_edgedetect ();

wire fle;
reg clk,rst,data_in;

edgedetect u1(clk,rst,data_in,fle);

initial begin clk = 0; forever #10 clk = ~clk; end

initial begin
	rst = 1;
	#20
	rst = 0;
	data_in = 1;
	#40
	data_in = 0;
	#40
	data_in = 1;
end

initial begin
	$dumpfile("tb_edgedetect.vcd");
	$dumpvars(0, tb_edgedetect);
	#120
	$finish;
end

endmodule

edgedetect/tb_edgedetect.vcd
$date
	Sat Jan 28 01:16:15 2023
$end
$version
	Icarus Verilog
$end
$timescale
	1ps
$end
$scope module tb_edgedetect $end
$var wire 1 ! fle $end
$var reg 1 " clk $end
$var reg 1 # data_in $end
$var reg 1 $ rst $end
$scope module u1 $end
$var wire 1 " clk $end
$var wire 1 # data_in $end
$var wire 1 $ rst $end
$var wire 1 % fallingedge $end
$var reg 1 ! fle $end
$var reg 3 & pipe [2:0] $end
$upscope $end
$upscope $end
$enddefinitions $end
#0
$dumpvars
bx &
x%
1$
x#
0"
x!
$end
#10000
0!
1"
#20000
0"
1#
0$
#30000
bx1 &
1"
#40000
0"
#50000
0%
bx11 &
1"
#60000
0"
0#
#70000
b110 &
1"
#80000
0"
#90000
1%
b100 &
1"
#100000
0"
1#
#110000
0%
1!
b1 &
1"
