onehot/top.v
// One Hot pattern generator
module top #(
       	parameter NUMWIDTH = 8
	)	
	(
	input 				clk,
	input				rst,
	output reg [NUMWIDTH-1:0] 	rot
);
	reg [NUMWIDTH-1:0]	tmp;
	


	always @(posedge clk or negedge rst) begin
		if (!rst) begin
			rot <= 'b0;
		end else begin
			if (rot[NUMWIDTH-1] == 1) begin
				rot <= 'b0;
			end else begin
				if (rot == 0) begin
					rot[0] <= 1;
				end else begin
					rot <= rot<<1;
				end
			end
		end
	end

endmodule

onehot/tb.v
module tb();

wire [NUM-1:0] rot;
reg clk,rst;
parameter NUM = 4;
top #(NUM) u1(clk, rst, rot);

initial begin clk = 0; forever #10 clk = !clk; end

initial begin
	rst = 1;
	#20
	rst = 0;
	#10
	rst = 1;
end

initial begin
	$dumpfile("output.vcd");
	$dumpvars;
	#500
	$finish;
end

endmodule

onehot/output.vcd
$date
	Sun Jan 15 10:19:37 2023
$end
$version
	Icarus Verilog
$end
$timescale
	1s
$end
$scope module tb $end
$var wire 4 ! rot [3:0] $end
$var reg 1 " clk $end
$var reg 1 # rst $end
$scope module u1 $end
$var wire 1 " clk $end
$var wire 1 # rst $end
$var reg 4 $ rot [3:0] $end
$upscope $end
$upscope $end
$enddefinitions $end
#0
$dumpvars
bx $
1#
0"
bx !
$end
#10
bx0 !
bx0 $
1"
#20
b0 !
b0 $
0"
0#
#30
b1 !
b1 $
1"
1#
#40
0"
#50
b10 !
b10 $
1"
#60
0"
#70
b100 !
b100 $
1"
#80
0"
#90
b1000 !
b1000 $
1"
#100
0"
#110
b0 !
b0 $
1"
#120
0"
#130
b1 !
b1 $
1"
#140
0"
#150
b10 !
b10 $
1"
#160
0"
#170
b100 !
b100 $
1"
#180
0"
#190
b1000 !
b1000 $
1"
#200
0"
#210
b0 !
b0 $
1"
#220
0"
#230
b1 !
b1 $
1"
#240
0"
#250
b10 !
b10 $
1"
#260
0"
#270
b100 !
b100 $
1"
#280
0"
#290
b1000 !
b1000 $
1"
#300
0"
#310
b0 !
b0 $
1"
#320
0"
#330
b1 !
b1 $
1"
#340
0"
#350
b10 !
b10 $
1"
#360
0"
#370
b100 !
b100 $
1"
#380
0"
#390
b1000 !
b1000 $
1"
#400
0"
#410
b0 !
b0 $
1"
#420
0"
#430
b1 !
b1 $
1"
#440
0"
#450
b10 !
b10 $
1"
#460
0"
#470
b100 !
b100 $
1"
#480
0"
#490
b1000 !
b1000 $
1"
